odoo/addons/float_align_at_decimal/LICENSE
odoo/addons/float_align_at_decimal/__init__.py
odoo/addons/float_align_at_decimal/__manifest__.py
odoo/addons/float_align_at_decimal/images/screen.png
odoo/addons/float_align_at_decimal/models/__init__.py
odoo/addons/float_align_at_decimal/models/ir_qweb_fields.py
odoo/addons/float_align_at_decimal/static/description/icon.png
odoo/addons/float_align_at_decimal/tests/TEST_INSTRUCTIONS.rst
odoo_addon_float_align_at_decimal-16.0.1.0.0.dist-info/METADATA
odoo_addon_float_align_at_decimal-16.0.1.0.0.dist-info/WHEEL
odoo_addon_float_align_at_decimal-16.0.1.0.0.dist-info/top_level.txt
odoo_addon_float_align_at_decimal-16.0.1.0.0.dist-info/RECORD
